dogtor/__init__.py
dogtor/env.py
dogtor/project.py
dogtor/utils.py
dogtor-0.2.0.dist-info/LICENCE
dogtor-0.2.0.dist-info/METADATA
dogtor-0.2.0.dist-info/WHEEL
dogtor-0.2.0.dist-info/entry_points.txt
dogtor-0.2.0.dist-info/RECORD
