Metadata-Version: 2.3
Name: dogtor
Version: 0.2.0
Summary: Python project scaffolding tool.
Author: Suman Saurabh
Author-email: sumanan047@gmail.com
Requires-Python: >=3.9,<4.0
Classifier: Programming Language :: Python :: 3
Classifier: Programming Language :: Python :: 3.9
Classifier: Programming Language :: Python :: 3.10
Classifier: Programming Language :: Python :: 3.11
Classifier: Programming Language :: Python :: 3.12
Classifier: Programming Language :: Python :: 3.13
